{
  "id": 52,
  "category": "tips-eating-out-takeout-guide",
  "theme": "Understanding Eating Out Takeout Guide Tips",
  "tone": "academic",
  "title": "The Future of Eating Out Takeout Guide Tips: What to Expect",
  "slug": "the-future-of-eating-out-takeout-guide-tips-what-to-expect",
  "meta_description": "Take your knowledge of Understanding Eating Out Takeout Guide Tips to the next level with our detailed guide. Comprehensive coverage of all essential aspects.",
  "content": "The following instructional sequence is designed to facilitate the acquisition of mastery in Understanding Eating Out Takeout Guide Tips. By adhering to these rigorous steps, practitioners can achieve standardized proficiency.\n\n<h2>What is Understanding Eating Out Takeout Guide Tips?</h2>\n<p>Let's start with the basics: what exactly is this subject all about? We'll explore the core definitions and key concepts that form the foundation of this fascinating topic. Understanding these fundamentals is crucial for everything that follows.</p>\n\n<h2>Getting Started</h2>\n<p>This is one of the fundamental building blocks for future success.</p>\n<p>Learn how to begin your journey with practical, actionable steps. This section provides a clear roadmap to help you get started on the right foot and avoid common pitfalls that many beginners encounter.</p>\n\n📌 **Quick Fact**: Unusual: In some cultures, this is considered a foundational skill for all citizens.\n\n<h2>The Advantages</h2>\n<p>Understanding the benefits helps us appreciate the value of this subject. In this section, we'll examine the positive impacts and advantages you can expect to gain from your learning journey. While simple on the surface, this has profound implications when applied.</p>\n\n📖 **Real World Application**: One practitioner started with just 15 minutes per day and saw significant improvements within 3 weeks. They credit their success to consistent practice and applying what they learned immediately.\n\n<h2>Best Practices</h2>\n<p>What do the experts recommend? Let's look at proven strategies and best practices that have stood the test of time. Implementing these will help you achieve better results more efficiently. Take the time to internalize this information—it will serve you well.</p>\n\n📌 **Quick Fact**: Little known: There are at least 12 different schools of thought on this topic.\n\n<h2>Advanced Techniques</h2>\n<p>Ready to take things to the next level? This section covers more advanced techniques and approaches for those who want to deepen their expertise and go beyond the basics.</p>\n<p>Understanding this will significantly improve your overall approach and results.</p>\n\n<h2>Practical Instructions</h2>\n<p>This is one of the fundamental building blocks for future success.</p>\n<p>Let's break this down into manageable steps that anyone can follow. This comprehensive guide takes you from start to finish, explaining each phase clearly.</p>\n\n<h3>Quick Checklist</h3>\n<ul>\n  <li>Define clear goals before you start</li>\n  <li>Break complex tasks into manageable steps</li>\n  <li>Celebrate small wins along the way</li>\n  <li>Learn from mistakes and adapt quickly</li>\n  <li>Share knowledge and collaborate with others</li>\n</ul>\n\n<h2>Going Further</h2>\n<p>Once you've mastered the fundamentals, what's next? Let's explore advanced techniques and strategies that will help you elevate your skills and knowledge to new heights.</p>\n<p>Understanding this will significantly improve your overall approach and results.</p>\n<p>Celebrate your progress, no matter how small it may seem.</p>\n\n<h2>Ask the Experts</h2>\n<p>We've gathered the most frequently asked questions about this topic and provided thorough, expert answers. This covers the questions people most often have when starting out.</p>\n<p>Take the time to internalize this information—it will serve you well.</p>\n\n<h2>Common Questions</h2>\n<p>Got questions? We've got answers. This section addresses the most common inquiries and provides valuable perspectives from experienced practitioners.</p>\n\n<h2>Different Approaches</h2>\n<p>There are multiple ways to approach this topic, each with its own strengths. This section compares different methodologies to help you choose what works best for you. This is a key concept that deserves your full attention and practice.</p>\n\n<h2>Walkthrough</h2>\n<p>Let's break this down into manageable steps that anyone can follow. This comprehensive guide takes you from start to finish, explaining each phase clearly.</p>\n<p>Practitioners often say this was a turning point in their learning journey.</p>\n\n<h2>Potential Pitfalls</h2>\n<p>Understand the obstacles you might face and how to overcome them. Every journey has its hurdles, but with the right knowledge and preparation, you can navigate them successfully and stay on track.</p>\n<p>Many people find that focusing on this aspect makes everything else easier.</p>\n<p>Don't be afraid to experiment and find what works best for you.</p>\n\nWe'll leave you with this final thought on Understanding Eating Out Takeout Guide Tips: the only limit to your success is the one you set for yourself. Break through those barriers, challenge your assumptions, and keep pushing for excellence. The world of Understanding Eating Out Takeout Guide Tips is yours to explore and conquer!",
  "created_at": "2026-06-05T17:29:20.324159",
  "word_count": 683,
  "seo": {
    "keywords": [
      "understanding eating out takeout guide tips",
      "tips-eating-out-takeout-guide",
      "Understanding Eating Out Takeout Guide Tips guide",
      "best Understanding Eating Out Takeout Guide Tips",
      "Understanding Eating Out Takeout Guide Tips tips",
      "Understanding Eating Out Takeout Guide Tips 2026",
      "how to understanding eating out takeout guide tips"
    ],
    "title_tag": "The Future of Eating Out Takeout Guide Tips: What to Expect | eating-out-takeout-guide",
    "meta_description": "Take your knowledge of Understanding Eating Out Takeout Guide Tips to the next level with our detailed guide. Comprehensive coverage of all essential aspects.",
    "og_title": "The Future of Eating Out Takeout Guide Tips: What to Expect",
    "og_description": "Take your knowledge of Understanding Eating Out Takeout Guide Tips to the next level with our detailed guide. Comprehensive coverage of all essential aspects.",
    "og_type": "article",
    "twitter_card": "summary_large_image",
    "canonical_url": "/the-future-of-eating-out-takeout-guide-tips-what-to-expect",
    "robots": "index, follow"
  },
  "geo": {
    "country": "United States",
    "city": "Los Angeles",
    "language": "en",
    "target_regions": [
      "North America",
      "Europe",
      "Asia Pacific"
    ]
  },
  "image": {
    "id": "1cbae39c3dbae4eb189ba3e7677727c8c6ba57b74b9ab47db8806950af709064",
    "url": "https://picsum.photos/815/400?random=957",
    "alt": "Featured image for: The Future of Eating Out Takeout Guide Tips: What to Expect",
    "width": 815,
    "height": 400
  }
}