{
  "id": 96,
  "category": "tutorials-eating-out-takeout-guide",
  "theme": "Eating Out Takeout Guide Tutorials for Beginners",
  "tone": "storytelling",
  "title": "Eating Out Takeout Guide Tutorials for Beginners: Common Mistakes and How to Avoid Them",
  "slug": "eating-out-takeout-guide-tutorials-for-beginners-common-mistakes-and-how-to-avoid-them",
  "meta_description": "Learn about Eating Out Takeout Guide Tutorials for Beginners from the ground up. Our comprehensive guide covers everything you need to start your journey with confidence.",
  "content": "If you had told me five years ago that I'd be writing about Eating Out Takeout Guide Tutorials for Beginners, I wouldn't have believed you. But here we are, and the journey has been incredible.\n\nAt first, everything about Eating Out Takeout Guide Tutorials for Beginners seemed daunting. I struggled to understand the basics, and I almost gave up multiple times. The challenges were real, but so was my determination to master it.\n\n<h2>What to Watch For</h2>\n<p>No learning process is without challenges. Let's identify common obstacles you might encounter and, more importantly, learn how to overcome them effectively.</p>\n<p>While simple on the surface, this has profound implications when applied.</p>\n\n<h2>Common Misconceptions</h2>\n<p>There are many myths and misunderstandings surrounding this topic. Let's set the record straight by addressing common misconceptions and separating fact from fiction.</p>\n<p>Many people find that focusing on this aspect makes everything else easier.</p>\n<p>Remember that consistency matters more than intensity.</p>\n\n<h2>Historical Context</h2>\n<p>From humble beginnings to widespread adoption, the story of how this subject developed is fascinating and informative. We trace its journey through time.</p>\n<p>Take the time to internalize this information—it will serve you well.</p>\n\nThen came the breakthrough. I realized that Eating Out Takeout Guide Tutorials for Beginners isn't just about techniques—it's about a mindset. Once I understood that, everything started falling into place.\n\n<h2>What's Next</h2>\n<p>The only constant is change. Let's explore what the future might hold for this subject, including emerging trends, new technologies, and evolving best practices you should be aware of. Understanding this will significantly improve your overall approach and results.</p>\n\n<h2>Setting the Record Straight</h2>\n<p>There are many myths and misunderstandings surrounding this topic. Let's set the record straight by addressing common misconceptions and separating fact from fiction.</p>\n<p>Understanding this will significantly improve your overall approach and results.</p>\n<p>Celebrate your progress, no matter how small it may seem.</p>\n\n<h2>In Practice</h2>\n<p>This is one of the fundamental building blocks for future success.</p>\n<p>Nothing beats seeing concepts in action. This section explores real-world examples and case studies that demonstrate how these principles work in practical situations. Learn from actual success stories.</p>\n\n<h2>Beginner's Guide</h2>\n<p>While simple on the surface, this has profound implications when applied.</p>\n<p>Learn how to begin your journey with practical, actionable steps. This section provides a clear roadmap to help you get started on the right foot and avoid common pitfalls that many beginners encounter.</p>\n\n<h2>Setting the Record Straight</h2>\n<p>There are many myths and misunderstandings surrounding this topic. Let's set the record straight by addressing common misconceptions and separating fact from fiction.</p>\n\n<h2>Different Approaches</h2>\n<p>Not every approach works for everyone. Here, we look at various strategies and discuss when to use which method for optimal results.</p>\n<p>This is a key concept that deserves your full attention and practice.</p>\n<p>The more you practice this, the more natural it will become.</p>\n\n<h2>What to Watch For</h2>\n<p>Understand the obstacles you might face and how to overcome them. Every journey has its hurdles, but with the right knowledge and preparation, you can navigate them successfully and stay on track.</p>\n<p>While simple on the surface, this has profound implications when applied.</p>\n\n<h2>First Steps</h2>\n<p>Ready to begin? Let's walk through the essential first steps you need to take. This practical guide will help you navigate the initial stages with confidence and set you up for success.</p>\n\n<h2>Future Outlook</h2>\n<p>What does tomorrow hold? In this section, we'll look at the future direction of this field, emerging trends to watch, and how you can prepare for what's coming next.</p>\n<p>This is one of the fundamental building blocks for future success.</p>\n\n<h2>Walkthrough</h2>\n<p>Let's break this down into manageable steps that anyone can follow. This comprehensive guide takes you from start to finish, explaining each phase clearly.</p>\n<p>This is one of the fundamental building blocks for future success.</p>\n<p>Small, daily improvements lead to big results over time.</p>\n\nThe key to success in Eating Out Takeout Guide Tutorials for Beginners lies in your hands. We've provided the roadmap, but you must take the steps. Start today, stay focused, and watch as your understanding and skills grow beyond your expectations. Your future self will thank you for the effort you put in now.",
  "created_at": "2026-06-05T17:29:20.335487",
  "word_count": 691,
  "seo": {
    "keywords": [
      "eating out takeout guide tutorials for beginners",
      "tutorials-eating-out-takeout-guide",
      "Eating Out Takeout Guide Tutorials for Beginners guide",
      "best Eating Out Takeout Guide Tutorials for Beginners",
      "Eating Out Takeout Guide Tutorials for Beginners tips",
      "Eating Out Takeout Guide Tutorials for Beginners 2026",
      "how to eating out takeout guide tutorials for beginners"
    ],
    "title_tag": "Eating Out Takeout Guide Tutorials for Beginners: Common Mistakes and How to Avoid Them | eating-out-takeout-guide",
    "meta_description": "Learn about Eating Out Takeout Guide Tutorials for Beginners from the ground up. Our comprehensive guide covers everything you need to start your journey with confidence.",
    "og_title": "Eating Out Takeout Guide Tutorials for Beginners: Common Mistakes and How to Avoid Them",
    "og_description": "Learn about Eating Out Takeout Guide Tutorials for Beginners from the ground up. Our comprehensive guide covers everything you need to start your journey with confidence.",
    "og_type": "article",
    "twitter_card": "summary_large_image",
    "canonical_url": "/eating-out-takeout-guide-tutorials-for-beginners-common-mistakes-and-how-to-avoid-them",
    "robots": "index, follow"
  },
  "geo": {
    "country": "France",
    "city": "Paris",
    "language": "en",
    "target_regions": [
      "North America",
      "Europe",
      "Asia Pacific"
    ]
  },
  "image": {
    "id": "2d6604fdb9b39c732b88f47151c1c35d3d825d2a10f250dc9534add30e10793f",
    "url": "https://picsum.photos/813/564?random=429",
    "alt": "Featured image for: Eating Out Takeout Guide Tutorials for Beginners: Common Mistakes and How to Avoid Them",
    "width": 813,
    "height": 564
  }
}